GeneLearn/__init__.py
GeneLearn-0.0.0.dist-info/LICENSE
GeneLearn-0.0.0.dist-info/WHEEL
GeneLearn-0.0.0.dist-info/METADATA
GeneLearn-0.0.0.dist-info/RECORD
